dbt_command_center/__init__.py
dbt_command_center/index.html
dbt_command_center/main.py
dbt_command_center/montara_http.py
dbt_command_center-0.1.22.dist-info/LICENSE
dbt_command_center-0.1.22.dist-info/METADATA
dbt_command_center-0.1.22.dist-info/WHEEL
dbt_command_center-0.1.22.dist-info/entry_points.txt
dbt_command_center-0.1.22.dist-info/top_level.txt
dbt_command_center-0.1.22.dist-info/RECORD
