Metadata-Version: 2.1
Name: dbt-command-center
Version: 0.1.22
Summary: Stop drilling through dbt logs and start visualizing them
Author: Montara team
Author-email: support@montara.io
Classifier: Programming Language :: Python :: 3
Classifier: License :: OSI Approved :: MIT License
Classifier: Operating System :: OS Independent
Requires-Python: >=3.6
License-File: LICENSE
Requires-Dist: jsonlines
